ulia/__init__.py
ulia/routines.py
ulia/tests/__init__.py
ulia/tests/routines_test.py
ulia-2023.2.1.dist-info/LICENSE
ulia-2023.2.1.dist-info/METADATA
ulia-2023.2.1.dist-info/WHEEL
ulia-2023.2.1.dist-info/top_level.txt
ulia-2023.2.1.dist-info/RECORD
