Metadata-Version: 2.1
Name: ulia
Version: 2023.2.1
Summary: Algorithm to emulate a lock-in amplifier
Home-page: https://gitlab.com/UhlDaniel/ulia
Author: Daniel Uhl
Author-email: daniel_uhl@hotmail.de
Maintainer: Daniel Uhl
Maintainer-email: daniel_uhl@hotmail.de
License: MIT
Keywords: lia lock-in amplifier
Platform: UNKNOWN
Classifier: Programming Language :: Python :: 3
Classifier: License :: OSI Approved :: MIT License
Classifier: Operating System :: OS Independent
Requires-Python: >=3.6
License-File: LICENSE
Requires-Dist: numpy (>=1.14)
Requires-Dist: scipy (>=1.4)
Requires-Dist: numba (>=0.52)
